{
	"format_version": "1.8.0",
	"animations": {
		"animation.npc_icon.loop": {
			"loop": true,
			"animation_length": 2,
			"bones": {
				"scroll_2": {
					"rotation": {
						"0.0": [
							0,
							0,
							0
						],
						"0.3333": [
							-360,
							0,
							0
						],
						"1.25": [
							-360,
							0,
							0
						],
						"2.0": [
							0,
							0,
							0
						]
					},
					"scale": {
						"0.0": [
							1,
							1,
							1
						],
						"0.3333": [
							1,
							0,
							0
						],
						"1.25": [
							1,
							0,
							0
						],
						"2.0": [
							1,
							1,
							1
						]
					}
				},
				"scroll_1": {
					"rotation": {
						"0.0": [
							0,
							0,
							0
						],
						"0.3333": [
							-360,
							0,
							0
						],
						"1.25": [
							-360,
							0,
							0
						],
						"2.0": [
							0,
							0,
							0
						]
					},
					"scale": 1
				},
				"duel_particle": {
					"scale": {
						"0.0": [
							0,
							0,
							0
						],
						"0.0417": [
							0,
							0,
							0
						],
						"0.125": [
							1,
							1,
							1
						],
						"0.1667": [
							1.12,
							1.12,
							1.12
						],
						"0.2083": [
							1,
							1,
							1
						],
						"0.25": [
							0,
							0,
							0
						],
						"2.0": [
							0,
							0,
							0
						]
					}
				},
				"duel_sword_1": {
					"rotation": {
						"0.0": [
							0,
							0,
							-60
						],
						"0.0833": [
							0,
							0,
							15
						],
						"2.0": [
							0,
							0,
							-60
						]
					}
				},
				"duel_sword_2": {
					"rotation": {
						"0.0": [
							0,
							0,
							60
						],
						"0.0833": [
							0,
							0,
							-15
						],
						"2.0": [
							0,
							0,
							60
						]
					}
				},
				"vendor_bag": {
					"scale": {
						"0.0": [
							1,
							1,
							1
						],
						"0.0833": [
							1.25,
							0.75,
							1.25
						],
						"0.125": [
							0.75,
							1.25,
							0.75
						],
						"0.1667": [
							1,
							1,
							1
						]
					}
				},
				"vendor_coin": {
					"rotation": {
						"0.0": [
							0,
							0,
							0
						],
						"0.2917": [
							90,
							"q.anim_time*1440",
							0
						],
						"1.25": [
							90,
							"q.anim_time*360",
							0
						],
						"1.5833": [
							0,
							0,
							0
						]
					},
					"position": {
						"0.0": [
							0,
							0,
							0
						],
						"0.0417": [
							0,
							4,
							0
						],
						"1.5417": [
							0,
							4,
							0
						],
						"1.5833": [
							0,
							0,
							0
						]
					}
				},
				"information_paper": {
					"scale": {
						"0.0": [
							1,
							0,
							1
						],
						"0.2083": [
							1,
							0,
							1
						],
						"0.25": [
							1,
							1.25,
							1
						],
						"0.3333": [
							1,
							1,
							1
						],
						"1.4167": [
							1,
							1,
							1
						],
						"1.5": [
							1,
							1.25,
							1
						],
						"1.5417": [
							1,
							0,
							1
						],
						"1.75": [
							1,
							0,
							1
						]
					}
				},
				"travel_target": {
					"scale": {
						"0.0417": [
							1,
							1,
							1
						],
						"0.0833": [
							1.5,
							1.5,
							1
						],
						"0.125": [
							1,
							1,
							1
						],
						"0.5": [
							1,
							1,
							1
						],
						"0.5417": [
							1.5,
							1.5,
							1
						],
						"0.5833": [
							1,
							1,
							1
						],
						"1.0": [
							1,
							1,
							1
						],
						"1.0417": [
							1.5,
							1.5,
							1
						],
						"1.0833": [
							1,
							1,
							1
						],
						"1.5": [
							1,
							1,
							1
						],
						"1.5417": [
							1.2921,
							1.2921,
							1
						],
						"1.5833": [
							1,
							1,
							1
						]
					}
				},
				"information_paperscroll_1": {
					"scale": {
						"0.0": [
							1,
							1,
							1
						],
						"0.2083": [
							1,
							1,
							1
						],
						"0.25": [
							1,
							0,
							0
						],
						"0.3333": [
							0,
							0,
							0
						],
						"1.4167": [
							0,
							0,
							0
						],
						"1.5": [
							1,
							0,
							0
						],
						"1.5417": [
							1,
							1,
							1
						],
						"1.75": [
							1,
							1,
							1
						]
					}
				}
			}
		},
		"animation.npc_icon.float": {
			"loop": true,
			"bones": {
				"root_icon": {
					"position": [
						0,
						"math.sin(q.anim_time*360)*0.5",
						0
					]
				}
			}
		}
	}
}